Flask_Lan/__init__.py
Flask_Lan/core.py
Flask_Lan/openapi.py
Flask_Lan/py.typed
Flask_Lan/schemas.py
Flask_Lan/utils.py
Flask_Lan/validate.py
Flask_Lan/wraps.py
Flask_Lan/templates/__init__.py
Flask_Lan/templates/redoc.html
Flask_Lan/templates/swagger.html
flask_lan-0.1.12.dist-info/METADATA
flask_lan-0.1.12.dist-info/WHEEL
flask_lan-0.1.12.dist-info/licenses/LICENSE
flask_lan-0.1.12.dist-info/RECORD
